ohmslaw/__init__.py
ohmslaw/__main__.py
ohmslaw/cli.py
ohmslaw/version.py
ohmslaw-2.1.2.dist-info/LICENSE
ohmslaw-2.1.2.dist-info/METADATA
ohmslaw-2.1.2.dist-info/WHEEL
ohmslaw-2.1.2.dist-info/entry_points.txt
ohmslaw-2.1.2.dist-info/top_level.txt
ohmslaw-2.1.2.dist-info/RECORD
